{
  "indexes": [
    {
      "collectionGroup": "accounts",
      "queryScope": "COLLECTION",
      "fields": [
        { "fieldPath": "stage", "order": "ASCENDING" },
        { "fieldPath": "createdAt", "order": "DESCENDING" }
      ]
    },
    {
      "collectionGroup": "deals",
      "queryScope": "COLLECTION",
      "fields": [
        { "fieldPath": "stage", "order": "ASCENDING" },
        { "fieldPath": "createdAt", "order": "DESCENDING" }
      ]
    },
    {
      "collectionGroup": "deals",
      "queryScope": "COLLECTION",
      "fields": [
        { "fieldPath": "accountId", "order": "ASCENDING" },
        { "fieldPath": "createdAt", "order": "DESCENDING" }
      ]
    },
    {
      "collectionGroup": "activities",
      "queryScope": "COLLECTION",
      "fields": [
        { "fieldPath": "type", "order": "ASCENDING" },
        { "fieldPath": "createdAt", "order": "DESCENDING" }
      ]
    },
    {
      "collectionGroup": "activities",
      "queryScope": "COLLECTION",
      "fields": [
        { "fieldPath": "accountId", "order": "ASCENDING" },
        { "fieldPath": "createdAt", "order": "DESCENDING" }
      ]
    },
    {
      "collectionGroup": "insights",
      "queryScope": "COLLECTION",
      "fields": [
        { "fieldPath": "type", "order": "ASCENDING" },
        { "fieldPath": "createdAt", "order": "DESCENDING" }
      ]
    },
    {
      "collectionGroup": "agentRuns",
      "queryScope": "COLLECTION",
      "fields": [
        { "fieldPath": "agentId", "order": "ASCENDING" },
        { "fieldPath": "startedAt", "order": "DESCENDING" }
      ]
    },
    {
      "collectionGroup": "agents",
      "queryScope": "COLLECTION",
      "fields": [
        { "fieldPath": "status", "order": "ASCENDING" },
        { "fieldPath": "createdAt", "order": "DESCENDING" }
      ]
    }
  ],
  "fieldOverrides": []
}
